sspipe/__init__.py
sspipe/compatibility.py
sspipe/facade.py
sspipe/patch.py
sspipe/pipe.py
sspipe/version.py
sspipe-0.1.17.dist-info/LICENSE
sspipe-0.1.17.dist-info/METADATA
sspipe-0.1.17.dist-info/WHEEL
sspipe-0.1.17.dist-info/top_level.txt
sspipe-0.1.17.dist-info/RECORD
