Metadata-Version: 2.1
Name: sspipe
Version: 0.1.17
Summary: Simple Smart Pipe Operator
Home-page: https://sspipe.github.io/
Author: Mohammad Hossein Sekhavat
Author-email: sekhavat17@gmail.com
License: UNKNOWN
Project-URL: Source, https://github.com/sspipe/sspipe
Keywords: pipe helper tool magrittr data science
Platform: UNKNOWN
Classifier: Development Status :: 3 - Alpha
Classifier: Intended Audience :: Developers
Classifier: Topic :: Software Development :: Build Tools
Classifier: License :: OSI Approved :: MIT License
Classifier: Programming Language :: Python :: 3
License-File: LICENSE
Requires-Dist: pipe (<2.0,>=1.0)
Provides-Extra: dev
Requires-Dist: check-manifest ; extra == 'dev'
Provides-Extra: test
Requires-Dist: coverage ; extra == 'test'
